README.md
setup.py
alas/__init__.py
alas/cli.py
alas.egg-info/PKG-INFO
alas.egg-info/SOURCES.txt
alas.egg-info/dependency_links.txt
alas.egg-info/entry_points.txt
alas.egg-info/requires.txt
alas.egg-info/top_level.txt
alas/cmd/__init__.py
alas/cmd/cmd_git.py
alas/cmd/cmd_ssh.py
alas/utils/__init__.py
alas/utils/ssh_config.py