Metadata-Version: 1.0
Name: alas
Version: 1.0.1
Summary: All Linux aliases and auto-completion manager.
Home-page: https://github.com/hieulq/alas
Author: Hieu LE
Author-email: sudo@rm-rf.cloud
License: Apache-2.0
Platform: UNKNOWN
